<!--

    This file is part of JEMMA - http://jemma.energy-home.org
    (C) Copyright 2013 Telecom Italia (http://www.telecomitalia.it)

    JEMMA is free software: you can redistribute it and/or modify
    it under the terms of the GNU Lesser General Public License (LGPL) version 3
    or later as published by the Free Software Foundation, which accompanies
    this distribution and is available at http://www.gnu.org/licenses/lgpl.html

    JEMMA is distributed in the hope that it will be useful,
    but WITHOUT ANY WARRANTY; without even the implied warranty of
    MERCHANTABILITY or FITNESS FOR A PARTICULAR PURPOSE.  See the
    GNU Lesser General Public License (LGPL) for more details.


-->
<root>
  <!---->
  <profileinformation>
    <profilesid>TA</profilesid>
    <description>Telecom Application Profile</description>
    <zigbeeprofileid>0107</zigbeeprofileid>
  </profileinformation>
  <!---->
  <devices>
    <profilesid>TA</profilesid>
    <deviceidentifier>0000</deviceidentifier>
    <description>ZigBee SIM Card</description>
  </devices>
  <devices>
    <profilesid>TA</profilesid>
    <deviceidentifier>0001</deviceidentifier>
    <description>ZigBee Mobile Terminal</description>
  </devices>
  <devices>
    <profilesid>TA</profilesid>
    <deviceidentifier>0005</deviceidentifier>
    <description>Configuration tool</description>
  </devices>
  <devices>
    <profilesid>TA</profilesid>
    <deviceidentifier>0008</deviceidentifier>
    <description>Range extender</description>
  </devices>
  <devices>
    <profilesid>TA</profilesid>
    <deviceidentifier>0100</deviceidentifier>
    <description>ZigBee Access Point (ZAP)</description>
  </devices>
  <devices>
    <profilesid>TA</profilesid>
    <deviceidentifier>0101</deviceidentifier>
    <description>ZigBee Information Node (ZIN)</description>
  </devices>
  <devices>
    <profilesid>TA</profilesid>
    <deviceidentifier>0102</deviceidentifier>
    <description>ZigBee Information Terminal (ZIT)</description>
  </devices>
  <devices>
    <profilesid>TA</profilesid>
    <deviceidentifier>0200</deviceidentifier>
    <description>Point of sale</description>
  </devices>
  <devices>
    <profilesid>TA</profilesid>
    <deviceidentifier>0201</deviceidentifier>
    <description>Ticketing machine</description>
  </devices>
  <devices>
    <profilesid>TA</profilesid>
    <deviceidentifier>0202</deviceidentifier>
    <description>Pay - controller</description>
  </devices>
  <devices>
    <profilesid>TA</profilesid>
    <deviceidentifier>0203</deviceidentifier>
    <description>Billing unit</description>
  </devices>
  <devices>
    <profilesid>TA</profilesid>
    <deviceidentifier>0204</deviceidentifier>
    <description>Charging unit</description>
  </devices>
  <devices>
    <profilesid>TA</profilesid>
    <deviceidentifier>0300</deviceidentifier>
    <description>ZigBee flash card</description>
  </devices>
  <devices>
    <profilesid>TA</profilesid>
    <deviceidentifier>0301</deviceidentifier>
    <description>ZigBee PC Smart Card Reader</description>
  </devices>
  <devices>
    <profilesid>TA</profilesid>
    <deviceidentifier>0400</deviceidentifier>
    <description>ZigBee headset</description>
  </devices>
  <devices>
    <profilesid>TA</profilesid>
    <deviceidentifier>0401</deviceidentifier>
    <description>ZigBee microphone</description>
  </devices>
  <devices>
    <profilesid>TA</profilesid>
    <deviceidentifier>0402</deviceidentifier>
    <description>ZigBee speaker</description>
  </devices>
  <devices>
    <profilesid>TA</profilesid>
    <deviceidentifier>0500</deviceidentifier>
    <description>RSSI Anchor Node (RAN)</description>
  </devices>
  <devices>
    <profilesid>TA</profilesid>
    <deviceidentifier>0501</deviceidentifier>
    <description>RSSI Location  Node (RLN)</description>
  </devices>
  <devices>
    <profilesid>TA</profilesid>
    <deviceidentifier>0502</deviceidentifier>
    <description>RSSI Location Gateway (RLG)</description>
  </devices>
  <devices>
    <profilesid>TA</profilesid>
    <deviceidentifier>0600</deviceidentifier>
    <description>Chatting Unit</description>
  </devices>
  <devices>
    <profilesid>TA</profilesid>
    <deviceidentifier>0601</deviceidentifier>
    <description>Chatting Station</description>
  </devices>
  <!---->
  <clusters>
    <clustersidentifier>0016</clustersidentifier>
    <description>Partition</description>
  </clusters>
  <clusters>
    <clustersidentifier>0615</clustersidentifier>
    <description>ISO7816 Protocol Tunnel</description>
  </clusters>
  <clusters>
    <clustersidentifier>0900</clustersidentifier>
    <description>Information</description>
  </clusters>
  <clusters>
    <clustersidentifier>0901</clustersidentifier>
    <description>Data sharing</description>
  </clusters>
  <clusters>
    <clustersidentifier>0902</clustersidentifier>
    <description>Gaming</description>
  </clusters>
  <clusters>
    <clustersidentifier>0903</clustersidentifier>
    <description>Data rate control</description>
  </clusters>
  <clusters>
    <clustersidentifier>0904</clustersidentifier>
    <description>Voice over ZigBee</description>
  </clusters>
  <clusters>
    <clustersidentifier>0905</clustersidentifier>
    <description>Chatting</description>
  </clusters>
  <clusters>
    <clustersidentifier>0A01</clustersidentifier>
    <description>Payment</description>
  </clusters>
  <clusters>
    <clustersidentifier>0a02</clustersidentifier>
    <description>Billing</description>
  </clusters>

  <clusters>
    <clustersidentifier>0015</clustersidentifier>
    <description>Commissioning</description>
  </clusters>
  
  <clusters>
    <clustersidentifier>0016</clustersidentifier>
    <description>Partition</description>
  </clusters>
  <clusters>
    <clustersidentifier>0017</clustersidentifier>
    <description>Alpha Secure Key Estabilishment (ASKE)</description>
  </clusters>
  <clusters>
    <clustersidentifier>0018</clustersidentifier>
    <description>Alpha Secure Access Control(ASAC)</description>
  </clusters>
  <clusters>
    <clustersidentifier>000b</clustersidentifier>
    <description>RSSI Location</description>
  </clusters>
  <clusters>
    <clustersidentifier>0000</clustersidentifier>
    <description>Basic</description>
  </clusters>
  <clusters>
    <clustersidentifier>0003</clustersidentifier>
    <description>Identify</description>
  </clusters>
  <clusters>
    <clustersidentifier>0004</clustersidentifier>
    <description>Groups</description>
  </clusters>
  <clusters>
    <clustersidentifier>0006</clustersidentifier>
    <description>On/Off</description>
  </clusters>
  <serveroptionallist>
    <deviceid>0000</deviceid>
    <clusterid>0015</clusterid>
  </serveroptionallist>
  <serveroptionallist>
    <deviceid>0000</deviceid>
    <clusterid>0900</clusterid>
  </serveroptionallist>
  <serveroptionallist>
    <deviceid>0000</deviceid>
    <clusterid>0A01</clusterid>
  </serveroptionallist>
  <serveroptionallist>
    <deviceid>0000</deviceid>
    <clusterid>0017</clusterid>
  </serveroptionallist>
  <serveroptionallist>
    <deviceid>0000</deviceid>
    <clusterid>0018</clusterid>
  </serveroptionallist>
  <serveroptionallist>
    <deviceid>0000</deviceid>
    <clusterid>0901</clusterid>
  </serveroptionallist>
  <serveroptionallist>
    <deviceid>0000</deviceid>
    <clusterid>0904</clusterid>
  </serveroptionallist>
  <serveroptionallist>
    <deviceid>0000</deviceid>
    <clusterid>0903</clusterid>
  </serveroptionallist>
  <serveroptionallist>
    <deviceid>0000</deviceid>
    <clusterid>0905</clusterid>
  </serveroptionallist>
  <serveroptionallist>
    <deviceid>0000</deviceid>
    <clusterid>0615</clusterid>
  </serveroptionallist>
  <serveroptionallist>
    <deviceid>0000</deviceid>
    <clusterid>000b</clusterid>
  </serveroptionallist>
  <!---->
  <clientmandatorylist>
    <deviceid>0000</deviceid>
    <clusterid>0000</clusterid>
  </clientmandatorylist>
  <clientmandatorylist>
    <deviceid>0000</deviceid>
    <clusterid>0003</clusterid>
  </clientmandatorylist>
  <clientmandatorylist>
    <deviceid>0000</deviceid>
    <clusterid>0615</clusterid>
  </clientmandatorylist>
  <!---->
  <clientoptionallist>
    <deviceid>0000</deviceid>
    <clusterid>0900</clusterid>
  </clientoptionallist>
  <clientoptionallist>
    <deviceid>0000</deviceid>
    <clusterid>0A01</clusterid>
  </clientoptionallist>
  <clientoptionallist>
    <deviceid>0000</deviceid>
    <clusterid>0a02</clusterid>
  </clientoptionallist>
  <clientoptionallist>
    <deviceid>0000</deviceid>
    <clusterid>0017</clusterid>
  </clientoptionallist>
  <clientoptionallist>
    <deviceid>0000</deviceid>
    <clusterid>0018</clusterid>
  </clientoptionallist>
  <clientoptionallist>
    <deviceid>0000</deviceid>
    <clusterid>0901</clusterid>
  </clientoptionallist>
  <clientoptionallist>
    <deviceid>0000</deviceid>
    <clusterid>0904</clusterid>
  </clientoptionallist>
  <clientoptionallist>
    <deviceid>0000</deviceid>
    <clusterid>0903</clusterid>
  </clientoptionallist>
  <clientoptionallist>
    <deviceid>0000</deviceid>
    <clusterid>0905</clusterid>
  </clientoptionallist>
  <!---->
  <!---->
  <servermandatorylist>
    <deviceid>0001</deviceid>
    <clusterid>0000</clusterid>
  </servermandatorylist>
  <!---->
  <serveroptionallist>
    <deviceid>0001</deviceid>
    <clusterid>0003</clusterid>
  </serveroptionallist>
  <serveroptionallist>
    <deviceid>0001</deviceid>
    <clusterid>0004</clusterid>
  </serveroptionallist>
  <serveroptionallist>
    <deviceid>0001</deviceid>
    <clusterid>0015</clusterid>
  </serveroptionallist>
  <serveroptionallist>
    <deviceid>0001</deviceid>
    <clusterid>0900</clusterid>
  </serveroptionallist>
  <serveroptionallist>
    <deviceid>0001</deviceid>
    <clusterid>0A01</clusterid>
  </serveroptionallist>
  <serveroptionallist>
    <deviceid>0001</deviceid>
    <clusterid>0017</clusterid>
  </serveroptionallist>
  <serveroptionallist>
    <deviceid>0001</deviceid>
    <clusterid>0018</clusterid>
  </serveroptionallist>
  <serveroptionallist>
    <deviceid>0001</deviceid>
    <clusterid>0901</clusterid>
  </serveroptionallist>
  <serveroptionallist>
    <deviceid>0001</deviceid>
    <clusterid>0903</clusterid>
  </serveroptionallist>
  <serveroptionallist>
    <deviceid>0001</deviceid>
    <clusterid>0904</clusterid>
  </serveroptionallist>
  <serveroptionallist>
    <deviceid>0001</deviceid>
    <clusterid>0902</clusterid>
  </serveroptionallist>
  <serveroptionallist>
    <deviceid>0001</deviceid>
    <clusterid>0905</clusterid>
  </serveroptionallist>
  <serveroptionallist>
    <deviceid>0001</deviceid>
    <clusterid>0615</clusterid>
  </serveroptionallist>
  <serveroptionallist>
    <deviceid>0001</deviceid>
    <clusterid>0016</clusterid>
  </serveroptionallist>
  <serveroptionallist>
    <deviceid>0001</deviceid>
    <clusterid>000b</clusterid>
  </serveroptionallist>
  <!---->
  <clientmandatorylist>
    <deviceid>0001</deviceid>
    <clusterid>0000</clusterid>
  </clientmandatorylist>
  <clientmandatorylist>
    <deviceid>0001</deviceid>
    <clusterid>0003</clusterid>
  </clientmandatorylist>
  <!---->
  <clientoptionallist>
    <deviceid>0001</deviceid>
    <clusterid>0900</clusterid>
  </clientoptionallist>
  <clientoptionallist>
    <deviceid>0001</deviceid>
    <clusterid>0A01</clusterid>
  </clientoptionallist>
  <clientoptionallist>
    <deviceid>0001</deviceid>
    <clusterid>0a02</clusterid>
  </clientoptionallist>
  <clientoptionallist>
    <deviceid>0001</deviceid>
    <clusterid>0017</clusterid>
  </clientoptionallist>
  <clientoptionallist>
    <deviceid>0001</deviceid>
    <clusterid>0018</clusterid>
  </clientoptionallist>
  <clientoptionallist>
    <deviceid>0001</deviceid>
    <clusterid>0901</clusterid>
  </clientoptionallist>
  <clientoptionallist>
    <deviceid>0001</deviceid>
    <clusterid>0903</clusterid>
  </clientoptionallist>
  <clientoptionallist>
    <deviceid>0001</deviceid>
    <clusterid>0904</clusterid>
  </clientoptionallist>
  <clientoptionallist>
    <deviceid>0001</deviceid>
    <clusterid>0902</clusterid>
  </clientoptionallist>
  <clientoptionallist>
    <deviceid>0001</deviceid>
    <clusterid>0905</clusterid>
  </clientoptionallist>
  <clientoptionallist>
    <deviceid>0001</deviceid>
    <clusterid>0615</clusterid>
  </clientoptionallist>
  <clientoptionallist>
    <deviceid>0001</deviceid>
    <clusterid>0016</clusterid>
  </clientoptionallist>
  <!---->
  <!---->
  <servermandatorylist>
    <deviceid>0005</deviceid>
    <clusterid>0000</clusterid>
  </servermandatorylist>
  <!---->
  <serveroptionallist>
    <deviceid>0005</deviceid>
    <clusterid>0003</clusterid>
  </serveroptionallist>
  <serveroptionallist>
    <deviceid>0005</deviceid>
    <clusterid>0004</clusterid>
  </serveroptionallist>
  <serveroptionallist>
    <deviceid>0005</deviceid>
    <clusterid>0015</clusterid>
  </serveroptionallist>
  <serveroptionallist>
    <deviceid>0005</deviceid>
    <clusterid>0017</clusterid>
  </serveroptionallist>
  <serveroptionallist>
    <deviceid>0005</deviceid>
    <clusterid>0018</clusterid>
  </serveroptionallist>
  <!---->
  <clientmandatorylist>
    <deviceid>0005</deviceid>
    <clusterid>0000</clusterid>
  </clientmandatorylist>
  <clientmandatorylist>
    <deviceid>0005</deviceid>
    <clusterid>0003</clusterid>
  </clientmandatorylist>
  <clientmandatorylist>
    <deviceid>0005</deviceid>
    <clusterid>0004</clusterid>
  </clientmandatorylist>
  <!---->
  <clientoptionallist>
    <deviceid>0005</deviceid>
    <clusterid>0900</clusterid>
  </clientoptionallist>
  <clientoptionallist>
    <deviceid>0005</deviceid>
    <clusterid>0903</clusterid>
  </clientoptionallist>
  <clientoptionallist>
    <deviceid>0005</deviceid>
    <clusterid>0901</clusterid>
  </clientoptionallist>
  <clientoptionallist>
    <deviceid>0005</deviceid>
    <clusterid>0A01</clusterid>
  </clientoptionallist>
  <clientoptionallist>
    <deviceid>0005</deviceid>
    <clusterid>0a02</clusterid>
  </clientoptionallist>
  <clientoptionallist>
    <deviceid>0005</deviceid>
    <clusterid>0904</clusterid>
  </clientoptionallist>
  <clientoptionallist>
    <deviceid>0005</deviceid>
    <clusterid>0017</clusterid>
  </clientoptionallist>
  <clientoptionallist>
    <deviceid>0005</deviceid>
    <clusterid>0018</clusterid>
  </clientoptionallist>
  <clientoptionallist>
    <deviceid>0005</deviceid>
    <clusterid>000b</clusterid>
  </clientoptionallist>
  <clientoptionallist>
    <deviceid>0005</deviceid>
    <clusterid>0016</clusterid>
  </clientoptionallist>
  <!---->
  <!---->
  <servermandatorylist>
    <deviceid>0008</deviceid>
    <clusterid>0000</clusterid>
  </servermandatorylist>
  <!---->
  <serveroptionallist>
    <deviceid>0008</deviceid>
    <clusterid>0003</clusterid>
  </serveroptionallist>
  <serveroptionallist>
    <deviceid>0008</deviceid>
    <clusterid>0004</clusterid>
  </serveroptionallist>
  <serveroptionallist>
    <deviceid>0008</deviceid>
    <clusterid>0015</clusterid>
  </serveroptionallist>
  <!---->
  <!---->
  <!---->
  <!---->
  <!---->
  <!---->
  <servermandatorylist>
    <deviceid>0100</deviceid>
    <clusterid>0000</clusterid>
  </servermandatorylist>
  <servermandatorylist>
    <deviceid>0100</deviceid>
    <clusterid>0900</clusterid>
  </servermandatorylist>
  <!---->
  <serveroptionallist>
    <deviceid>0100</deviceid>
    <clusterid>0003</clusterid>
  </serveroptionallist>
  <serveroptionallist>
    <deviceid>0100</deviceid>
    <clusterid>0004</clusterid>
  </serveroptionallist>
  <serveroptionallist>
    <deviceid>0100</deviceid>
    <clusterid>0015</clusterid>
  </serveroptionallist>
  <serveroptionallist>
    <deviceid>0100</deviceid>
    <clusterid>0A01</clusterid>
  </serveroptionallist>
  <serveroptionallist>
    <deviceid>0100</deviceid>
    <clusterid>0017</clusterid>
  </serveroptionallist>
  <serveroptionallist>
    <deviceid>0100</deviceid>
    <clusterid>0018</clusterid>
  </serveroptionallist>
  <serveroptionallist>
    <deviceid>0100</deviceid>
    <clusterid>0a02</clusterid>
  </serveroptionallist>
  <!---->
  <clientmandatorylist>
    <deviceid>0100</deviceid>
    <clusterid>0900</clusterid>
  </clientmandatorylist>
  <!---->
  <clientoptionallist>
    <deviceid>0100</deviceid>
    <clusterid>0A01</clusterid>
  </clientoptionallist>
  <clientoptionallist>
    <deviceid>0100</deviceid>
    <clusterid>0017</clusterid>
  </clientoptionallist>
  <clientoptionallist>
    <deviceid>0100</deviceid>
    <clusterid>0018</clusterid>
  </clientoptionallist>
  <clientoptionallist>
    <deviceid>0100</deviceid>
    <clusterid>0a02</clusterid>
  </clientoptionallist>
  <!---->
  <!---->
  <servermandatorylist>
    <deviceid>0101</deviceid>
    <clusterid>0000</clusterid>
  </servermandatorylist>
  <servermandatorylist>
    <deviceid>0101</deviceid>
    <clusterid>0900</clusterid>
  </servermandatorylist>
  <!---->
  <serveroptionallist>
    <deviceid>0101</deviceid>
    <clusterid>0003</clusterid>
  </serveroptionallist>
  <serveroptionallist>
    <deviceid>0101</deviceid>
    <clusterid>0004</clusterid>
  </serveroptionallist>
  <serveroptionallist>
    <deviceid>0101</deviceid>
    <clusterid>0015</clusterid>
  </serveroptionallist>
  <serveroptionallist>
    <deviceid>0101</deviceid>
    <clusterid>0a02</clusterid>
  </serveroptionallist>
  <serveroptionallist>
    <deviceid>0101</deviceid>
    <clusterid>0017</clusterid>
  </serveroptionallist>
  <serveroptionallist>
    <deviceid>0101</deviceid>
    <clusterid>0018</clusterid>
  </serveroptionallist>
  <!---->
  <!---->
  <!---->
  <clientoptionallist>
    <deviceid>0101</deviceid>
    <clusterid>0900</clusterid>
  </clientoptionallist>
  <clientoptionallist>
    <deviceid>0101</deviceid>
    <clusterid>0017</clusterid>
  </clientoptionallist>
  <clientoptionallist>
    <deviceid>0101</deviceid>
    <clusterid>0018</clusterid>
  </clientoptionallist>
  <!---->
  <!---->
  <servermandatorylist>
    <deviceid>0102</deviceid>
    <clusterid>0000</clusterid>
  </servermandatorylist>
  <!---->
  <serveroptionallist>
    <deviceid>0102</deviceid>
    <clusterid>0003</clusterid>
  </serveroptionallist>
  <serveroptionallist>
    <deviceid>0102</deviceid>
    <clusterid>0004</clusterid>
  </serveroptionallist>
  <serveroptionallist>
    <deviceid>0102</deviceid>
    <clusterid>0015</clusterid>
  </serveroptionallist>
  <!---->
  <clientmandatorylist>
    <deviceid>0102</deviceid>
    <clusterid>0900</clusterid>
  </clientmandatorylist>
  <!---->
  <!---->
  <!---->
  <!---->
  <servermandatorylist>
    <deviceid>0200</deviceid>
    <clusterid>0000</clusterid>
  </servermandatorylist>
  <servermandatorylist>
    <deviceid>0200</deviceid>
    <clusterid>0900</clusterid>
  </servermandatorylist>
  <servermandatorylist>
    <deviceid>0200</deviceid>
    <clusterid>0A01</clusterid>
  </servermandatorylist>
  <servermandatorylist>
    <deviceid>0200</deviceid>
    <clusterid>0017</clusterid>
  </servermandatorylist>
  <servermandatorylist>
    <deviceid>0200</deviceid>
    <clusterid>0018</clusterid>
  </servermandatorylist>
  <!---->
  <serveroptionallist>
    <deviceid>0200</deviceid>
    <clusterid>0003</clusterid>
  </serveroptionallist>
  <serveroptionallist>
    <deviceid>0200</deviceid>
    <clusterid>0004</clusterid>
  </serveroptionallist>
  <serveroptionallist>
    <deviceid>0200</deviceid>
    <clusterid>0015</clusterid>
  </serveroptionallist>
  <!---->
  <clientmandatorylist>
    <deviceid>0200</deviceid>
    <clusterid>0017</clusterid>
  </clientmandatorylist>
  <clientmandatorylist>
    <deviceid>0200</deviceid>
    <clusterid>0018</clusterid>
  </clientmandatorylist>
  <!---->
  <!---->
  <!---->
  <!---->
  <servermandatorylist>
    <deviceid>0201</deviceid>
    <clusterid>0000</clusterid>
  </servermandatorylist>
  <servermandatorylist>
    <deviceid>0201</deviceid>
    <clusterid>0900</clusterid>
  </servermandatorylist>
  <servermandatorylist>
    <deviceid>0201</deviceid>
    <clusterid>0A01</clusterid>
  </servermandatorylist>
  <servermandatorylist>
    <deviceid>0201</deviceid>
    <clusterid>0017</clusterid>
  </servermandatorylist>
  <servermandatorylist>
    <deviceid>0201</deviceid>
    <clusterid>0018</clusterid>
  </servermandatorylist>
  <!---->
  <serveroptionallist>
    <deviceid>0201</deviceid>
    <clusterid>0003</clusterid>
  </serveroptionallist>
  <serveroptionallist>
    <deviceid>0201</deviceid>
    <clusterid>0004</clusterid>
  </serveroptionallist>
  <serveroptionallist>
    <deviceid>0201</deviceid>
    <clusterid>0015</clusterid>
  </serveroptionallist>
  <!---->
  <clientmandatorylist>
    <deviceid>0201</deviceid>
    <clusterid>0017</clusterid>
  </clientmandatorylist>
  <clientmandatorylist>
    <deviceid>0201</deviceid>
    <clusterid>0018</clusterid>
  </clientmandatorylist>
  <!---->
  <!---->
  <!---->
  <!---->
  <servermandatorylist>
    <deviceid>0202</deviceid>
    <clusterid>0000</clusterid>
  </servermandatorylist>
  <servermandatorylist>
    <deviceid>0202</deviceid>
    <clusterid>0900</clusterid>
  </servermandatorylist>
  <servermandatorylist>
    <deviceid>0202</deviceid>
    <clusterid>0017</clusterid>
  </servermandatorylist>
  <servermandatorylist>
    <deviceid>0202</deviceid>
    <clusterid>0018</clusterid>
  </servermandatorylist>
  <!---->
  <serveroptionallist>
    <deviceid>0202</deviceid>
    <clusterid>0003</clusterid>
  </serveroptionallist>
  <serveroptionallist>
    <deviceid>0202</deviceid>
    <clusterid>0004</clusterid>
  </serveroptionallist>
  <serveroptionallist>
    <deviceid>0202</deviceid>
    <clusterid>0015</clusterid>
  </serveroptionallist>
  <serveroptionallist>
    <deviceid>0202</deviceid>
    <clusterid>0A01</clusterid>
  </serveroptionallist>
  <!---->
  <clientmandatorylist>
    <deviceid>0202</deviceid>
    <clusterid>0900</clusterid>
  </clientmandatorylist>
  <clientmandatorylist>
    <deviceid>0202</deviceid>
    <clusterid>0017</clusterid>
  </clientmandatorylist>
  <clientmandatorylist>
    <deviceid>0202</deviceid>
    <clusterid>0018</clusterid>
  </clientmandatorylist>
  <!---->
  <clientoptionallist>
    <deviceid>0202</deviceid>
    <clusterid>0A01</clusterid>
  </clientoptionallist>
  <!---->
  <!---->
  <servermandatorylist>
    <deviceid>0203</deviceid>
    <clusterid>0000</clusterid>
  </servermandatorylist>
  <servermandatorylist>
    <deviceid>0203</deviceid>
    <clusterid>0900</clusterid>
  </servermandatorylist>
  <servermandatorylist>
    <deviceid>0203</deviceid>
    <clusterid>0017</clusterid>
  </servermandatorylist>
  <servermandatorylist>
    <deviceid>0203</deviceid>
    <clusterid>0018</clusterid>
  </servermandatorylist>
  <servermandatorylist>
    <deviceid>0203</deviceid>
    <clusterid>0a02</clusterid>
  </servermandatorylist>
  <!---->
  <serveroptionallist>
    <deviceid>0203</deviceid>
    <clusterid>0003</clusterid>
  </serveroptionallist>
  <serveroptionallist>
    <deviceid>0203</deviceid>
    <clusterid>0004</clusterid>
  </serveroptionallist>
  <serveroptionallist>
    <deviceid>0203</deviceid>
    <clusterid>0015</clusterid>
  </serveroptionallist>
  <!---->
  <clientmandatorylist>
    <deviceid>0203</deviceid>
    <clusterid>0900</clusterid>
  </clientmandatorylist>
  <clientmandatorylist>
    <deviceid>0203</deviceid>
    <clusterid>0017</clusterid>
  </clientmandatorylist>
  <clientmandatorylist>
    <deviceid>0203</deviceid>
    <clusterid>0018</clusterid>
  </clientmandatorylist>
  <clientmandatorylist>
    <deviceid>0203</deviceid>
    <clusterid>0a02</clusterid>
  </clientmandatorylist>
  <!---->
  <!---->
  <!---->
  <!---->
  <servermandatorylist>
    <deviceid>0204</deviceid>
    <clusterid>0000</clusterid>
  </servermandatorylist>
  <servermandatorylist>
    <deviceid>0204</deviceid>
    <clusterid>0900</clusterid>
  </servermandatorylist>
  <servermandatorylist>
    <deviceid>0204</deviceid>
    <clusterid>0017</clusterid>
  </servermandatorylist>
  <servermandatorylist>
    <deviceid>0204</deviceid>
    <clusterid>0018</clusterid>
  </servermandatorylist>
  <servermandatorylist>
    <deviceid>0204</deviceid>
    <clusterid>0a02</clusterid>
  </servermandatorylist>
  <!---->
  <serveroptionallist>
    <deviceid>0204</deviceid>
    <clusterid>0003</clusterid>
  </serveroptionallist>
  <serveroptionallist>
    <deviceid>0204</deviceid>
    <clusterid>0004</clusterid>
  </serveroptionallist>
  <serveroptionallist>
    <deviceid>0204</deviceid>
    <clusterid>0015</clusterid>
  </serveroptionallist>
  <!---->
  <clientmandatorylist>
    <deviceid>0204</deviceid>
    <clusterid>0900</clusterid>
  </clientmandatorylist>
  <clientmandatorylist>
    <deviceid>0204</deviceid>
    <clusterid>0017</clusterid>
  </clientmandatorylist>
  <clientmandatorylist>
    <deviceid>0204</deviceid>
    <clusterid>0018</clusterid>
  </clientmandatorylist>
  <clientmandatorylist>
    <deviceid>0204</deviceid>
    <clusterid>0a02</clusterid>
  </clientmandatorylist>
  <!---->
  <!---->
  <!---->
  <!---->
  <servermandatorylist>
    <deviceid>0300</deviceid>
    <clusterid>0000</clusterid>
  </servermandatorylist>
  <servermandatorylist>
    <deviceid>0300</deviceid>
    <clusterid>0006</clusterid>
  </servermandatorylist>
  <!---->
  <serveroptionallist>
    <deviceid>0300</deviceid>
    <clusterid>0003</clusterid>
  </serveroptionallist>
  <serveroptionallist>
    <deviceid>0300</deviceid>
    <clusterid>0004</clusterid>
  </serveroptionallist>
  <serveroptionallist>
    <deviceid>0300</deviceid>
    <clusterid>0015</clusterid>
  </serveroptionallist>
  <serveroptionallist>
    <deviceid>0300</deviceid>
    <clusterid>0017</clusterid>
  </serveroptionallist>
  <serveroptionallist>
    <deviceid>0300</deviceid>
    <clusterid>0018</clusterid>
  </serveroptionallist>
  <serveroptionallist>
    <deviceid>0300</deviceid>
    <clusterid>0901</clusterid>
  </serveroptionallist>
  <serveroptionallist>
    <deviceid>0300</deviceid>
    <clusterid>0903</clusterid>
  </serveroptionallist>
  <serveroptionallist>
    <deviceid>0300</deviceid>
    <clusterid>0900</clusterid>
  </serveroptionallist>
  <serveroptionallist>
    <deviceid>0300</deviceid>
    <clusterid>0016</clusterid>
  </serveroptionallist>
  <!---->
  <!---->
  <!---->
  <clientoptionallist>
    <deviceid>0300</deviceid>
    <clusterid>0017</clusterid>
  </clientoptionallist>
  <clientoptionallist>
    <deviceid>0300</deviceid>
    <clusterid>0018</clusterid>
  </clientoptionallist>
  <clientoptionallist>
    <deviceid>0300</deviceid>
    <clusterid>0901</clusterid>
  </clientoptionallist>
  <clientoptionallist>
    <deviceid>0300</deviceid>
    <clusterid>0903</clusterid>
  </clientoptionallist>
  <clientoptionallist>
    <deviceid>0300</deviceid>
    <clusterid>0016</clusterid>
  </clientoptionallist>
  <!---->
  <!---->
  <servermandatorylist>
    <deviceid>0301</deviceid>
    <clusterid>0000</clusterid>
  </servermandatorylist>
  <servermandatorylist>
    <deviceid>0301</deviceid>
    <clusterid>0615</clusterid>
  </servermandatorylist>
  <!---->
  <serveroptionallist>
    <deviceid>0301</deviceid>
    <clusterid>0003</clusterid>
  </serveroptionallist>
  <serveroptionallist>
    <deviceid>0301</deviceid>
    <clusterid>0004</clusterid>
  </serveroptionallist>
  <serveroptionallist>
    <deviceid>0301</deviceid>
    <clusterid>0015</clusterid>
  </serveroptionallist>
  <serveroptionallist>
    <deviceid>0301</deviceid>
    <clusterid>0017</clusterid>
  </serveroptionallist>
  <serveroptionallist>
    <deviceid>0301</deviceid>
    <clusterid>0018</clusterid>
  </serveroptionallist>
  <!---->
  <!---->
  <!---->
  <clientoptionallist>
    <deviceid>0301</deviceid>
    <clusterid>0017</clusterid>
  </clientoptionallist>
  <clientoptionallist>
    <deviceid>0301</deviceid>
    <clusterid>0018</clusterid>
  </clientoptionallist>
  <!---->
  <!---->
  <servermandatorylist>
    <deviceid>0400</deviceid>
    <clusterid>0000</clusterid>
  </servermandatorylist>
  <servermandatorylist>
    <deviceid>0400</deviceid>
    <clusterid>0904</clusterid>
  </servermandatorylist>
  <!---->
  <serveroptionallist>
    <deviceid>0400</deviceid>
    <clusterid>0003</clusterid>
  </serveroptionallist>
  <serveroptionallist>
    <deviceid>0400</deviceid>
    <clusterid>0004</clusterid>
  </serveroptionallist>
  <serveroptionallist>
    <deviceid>0400</deviceid>
    <clusterid>0015</clusterid>
  </serveroptionallist>
  <serveroptionallist>
    <deviceid>0400</deviceid>
    <clusterid>0017</clusterid>
  </serveroptionallist>
  <serveroptionallist>
    <deviceid>0400</deviceid>
    <clusterid>0018</clusterid>
  </serveroptionallist>
  <!---->
  <clientmandatorylist>
    <deviceid>0400</deviceid>
    <clusterid>0904</clusterid>
  </clientmandatorylist>
  <!---->
  <clientoptionallist>
    <deviceid>0400</deviceid>
    <clusterid>0017</clusterid>
  </clientoptionallist>
  <clientoptionallist>
    <deviceid>0400</deviceid>
    <clusterid>0018</clusterid>
  </clientoptionallist>
  <!---->
  <!---->
  <servermandatorylist>
    <deviceid>0401</deviceid>
    <clusterid>0000</clusterid>
  </servermandatorylist>
  <!---->
  <serveroptionallist>
    <deviceid>0401</deviceid>
    <clusterid>0003</clusterid>
  </serveroptionallist>
  <serveroptionallist>
    <deviceid>0401</deviceid>
    <clusterid>0004</clusterid>
  </serveroptionallist>
  <serveroptionallist>
    <deviceid>0401</deviceid>
    <clusterid>0015</clusterid>
  </serveroptionallist>
  <serveroptionallist>
    <deviceid>0401</deviceid>
    <clusterid>0017</clusterid>
  </serveroptionallist>
  <serveroptionallist>
    <deviceid>0401</deviceid>
    <clusterid>0018</clusterid>
  </serveroptionallist>
  <!---->
  <clientmandatorylist>
    <deviceid>0401</deviceid>
    <clusterid>0904</clusterid>
  </clientmandatorylist>
  <!---->
  <clientoptionallist>
    <deviceid>0401</deviceid>
    <clusterid>0017</clusterid>
  </clientoptionallist>
  <clientoptionallist>
    <deviceid>0401</deviceid>
    <clusterid>0018</clusterid>
  </clientoptionallist>
  <!---->
  <!---->
  <servermandatorylist>
    <deviceid>0402</deviceid>
    <clusterid>0000</clusterid>
  </servermandatorylist>
  <servermandatorylist>
    <deviceid>0402</deviceid>
    <clusterid>0904</clusterid>
  </servermandatorylist>
  <!---->
  <serveroptionallist>
    <deviceid>0402</deviceid>
    <clusterid>0003</clusterid>
  </serveroptionallist>
  <serveroptionallist>
    <deviceid>0402</deviceid>
    <clusterid>0004</clusterid>
  </serveroptionallist>
  <serveroptionallist>
    <deviceid>0402</deviceid>
    <clusterid>0015</clusterid>
  </serveroptionallist>
  <serveroptionallist>
    <deviceid>0402</deviceid>
    <clusterid>0017</clusterid>
  </serveroptionallist>
  <serveroptionallist>
    <deviceid>0402</deviceid>
    <clusterid>0018</clusterid>
  </serveroptionallist>
  <!---->
  <!---->
  <!---->
  <clientoptionallist>
    <deviceid>0402</deviceid>
    <clusterid>0017</clusterid>
  </clientoptionallist>
  <clientoptionallist>
    <deviceid>0402</deviceid>
    <clusterid>0018</clusterid>
  </clientoptionallist>
  <!---->
  <!---->
  <servermandatorylist>
    <deviceid>0500</deviceid>
    <clusterid>0000</clusterid>
  </servermandatorylist>
  <!---->
  <serveroptionallist>
    <deviceid>0500</deviceid>
    <clusterid>0003</clusterid>
  </serveroptionallist>
  <serveroptionallist>
    <deviceid>0500</deviceid>
    <clusterid>0004</clusterid>
  </serveroptionallist>
  <serveroptionallist>
    <deviceid>0500</deviceid>
    <clusterid>0015</clusterid>
  </serveroptionallist>
  <!---->
  <clientmandatorylist>
    <deviceid>0500</deviceid>
    <clusterid>000b</clusterid>
  </clientmandatorylist>
  <!---->
  <!---->
  <!---->
  <!---->
  <servermandatorylist>
    <deviceid>0501</deviceid>
    <clusterid>0000</clusterid>
  </servermandatorylist>
  <servermandatorylist>
    <deviceid>0501</deviceid>
    <clusterid>000b</clusterid>
  </servermandatorylist>
  <!---->
  <serveroptionallist>
    <deviceid>0501</deviceid>
    <clusterid>0003</clusterid>
  </serveroptionallist>
  <serveroptionallist>
    <deviceid>0501</deviceid>
    <clusterid>0004</clusterid>
  </serveroptionallist>
  <serveroptionallist>
    <deviceid>0501</deviceid>
    <clusterid>0015</clusterid>
  </serveroptionallist>
  <!---->
  <!---->
  <!---->
  <!---->
  <!---->
  <!---->
  <servermandatorylist>
    <deviceid>0502</deviceid>
    <clusterid>0000</clusterid>
  </servermandatorylist>
  <!---->
  <serveroptionallist>
    <deviceid>0502</deviceid>
    <clusterid>0003</clusterid>
  </serveroptionallist>
  <serveroptionallist>
    <deviceid>0502</deviceid>
    <clusterid>0004</clusterid>
  </serveroptionallist>
  <serveroptionallist>
    <deviceid>0502</deviceid>
    <clusterid>0015</clusterid>
  </serveroptionallist>
  <!---->
  <clientmandatorylist>
    <deviceid>0502</deviceid>
    <clusterid>000b</clusterid>
  </clientmandatorylist>
  <!---->
  <!---->
  <!---->
  <!---->
  <servermandatorylist>
    <deviceid>0600</deviceid>
    <clusterid>0000</clusterid>
  </servermandatorylist>
  <servermandatorylist>
    <deviceid>0600</deviceid>
    <clusterid>0905</clusterid>
  </servermandatorylist>
  <!---->
  <serveroptionallist>
    <deviceid>0600</deviceid>
    <clusterid>0003</clusterid>
  </serveroptionallist>
  <serveroptionallist>
    <deviceid>0600</deviceid>
    <clusterid>0004</clusterid>
  </serveroptionallist>
  <serveroptionallist>
    <deviceid>0600</deviceid>
    <clusterid>0015</clusterid>
  </serveroptionallist>
  <!---->
  <clientmandatorylist>
    <deviceid>0600</deviceid>
    <clusterid>0905</clusterid>
  </clientmandatorylist>
  <!---->
  <!---->
  <!---->
  <!---->
  <servermandatorylist>
    <deviceid>0601</deviceid>
    <clusterid>0000</clusterid>
  </servermandatorylist>
  <servermandatorylist>
    <deviceid>0601</deviceid>
    <clusterid>0905</clusterid>
  </servermandatorylist>
  <!---->
  <serveroptionallist>
    <deviceid>0601</deviceid>
    <clusterid>0003</clusterid>
  </serveroptionallist>
  <serveroptionallist>
    <deviceid>0601</deviceid>
    <clusterid>0004</clusterid>
  </serveroptionallist>
  <serveroptionallist>
    <deviceid>0601</deviceid>
    <clusterid>0015</clusterid>
  </serveroptionallist>
  <!---->
  <!---->
  <!---->
  <!---->
</root>